mdlearn/__init__.py
mdlearn/cli.py
mdlearn/metrics.py
mdlearn/utils.py
mdlearn/visualize.py
mdlearn/data/__init__.py
mdlearn/data/utils.py
mdlearn/data/datasets/__init__.py
mdlearn/data/datasets/contact_map.py
mdlearn/data/datasets/feature_vector.py
mdlearn/data/datasets/point_cloud.py
mdlearn/data/datasets/time_contact_map.py
mdlearn/data/preprocess/__init__.py
mdlearn/data/preprocess/simulation.py
mdlearn/data/preprocess/align/__init__.py
mdlearn/data/preprocess/align/iterative_means_align.py
mdlearn/data/preprocess/align/kabsch_align.py
mdlearn/data/preprocess/decorrelation/__init__.py
mdlearn/data/preprocess/decorrelation/spatial.py
mdlearn/data/preprocess/decorrelation/temporal.py
mdlearn/nn/__init__.py
mdlearn/nn/utils.py
mdlearn/nn/models/__init__.py
mdlearn/nn/models/lstm.py
mdlearn/nn/models/aae/__init__.py
mdlearn/nn/models/aae/model.py
mdlearn/nn/models/aae/point_3d_aae.py
mdlearn/nn/models/ae/__init__.py
mdlearn/nn/models/ae/linear.py
mdlearn/nn/models/ae/lstm.py
mdlearn/nn/models/ae/model.py
mdlearn/nn/models/vae/__init__.py
mdlearn/nn/models/vae/model.py
mdlearn/nn/models/vae/symmetric_conv2d_vae.py
mdlearn/nn/models/vde/__init__.py
mdlearn/nn/models/vde/model.py
mdlearn/nn/models/vde/symmetric_conv2d_vde.py
mdlearn/nn/models/wae/__init__.py
mdlearn/nn/models/wae/model.py
mdlearn/nn/models/wae/symmetric_conv2d_wae.py
mdlearn/nn/modules/__init__.py
mdlearn/nn/modules/conv1d_encoder.py
mdlearn/nn/modules/conv2d_decoder.py
mdlearn/nn/modules/conv2d_encoder.py
mdlearn/nn/modules/dense_net.py
mdlearn/nn/modules/linear_decoder.py
mdlearn/nn/modules/linear_discriminator.py
mdlearn/nn/modules/lstm_net.py
mdlearn-1.0.5.dist-info/LICENSE
mdlearn-1.0.5.dist-info/METADATA
mdlearn-1.0.5.dist-info/WHEEL
mdlearn-1.0.5.dist-info/entry_points.txt
mdlearn-1.0.5.dist-info/top_level.txt
mdlearn-1.0.5.dist-info/RECORD
