Metadata-Version: 2.1
Name: mdlearn
Version: 1.0.5
Summary: Machine learning for molecular dynamics.
Author-email: Alexander Brace <abrace@anl.gov>, Heng Ma <heng.ma@anl.gov>, Debsindhu Bhowmik <bhowmikd@ornl.gov>, Chakra Chennubhotla <chakracs@pitt.edu>, Arvind Ramanathan <ramanathana@anl.gov>
License: MIT
Project-URL: homepage, https://github.com/ramanathanlab/mdlearn
Project-URL: documentation, https://mdlearn.readthedocs.io/en/latest
Project-URL: repository, https://github.com/ramanathanlab/mdlearn
Classifier: License :: OSI Approved :: MIT License
Classifier: Programming Language :: Python :: 3
Requires-Python: >=3.8
License-File: LICENSE
Requires-Dist: pyyaml
Requires-Dist: pydantic
Requires-Dist: h5py
Requires-Dist: pandas
Requires-Dist: numpy
Requires-Dist: tqdm
Requires-Dist: plotly
Requires-Dist: MDAnalysis
Requires-Dist: typer
Provides-Extra: dev
Requires-Dist: covdefaults >=2.2 ; extra == 'dev'
Requires-Dist: coverage ; extra == 'dev'
Requires-Dist: mypy ; extra == 'dev'
Requires-Dist: pre-commit ; extra == 'dev'
Requires-Dist: pytest ; extra == 'dev'
Requires-Dist: pytest-cov ; extra == 'dev'
Requires-Dist: ruff ; extra == 'dev'
Requires-Dist: tox ; extra == 'dev'
Requires-Dist: virtualenv ; extra == 'dev'
Requires-Dist: types-PyYAML ; extra == 'dev'
Requires-Dist: build ; extra == 'dev'
Requires-Dist: twine ; extra == 'dev'
Provides-Extra: docs
Requires-Dist: black ; extra == 'docs'
Requires-Dist: sphinx ==8.1.3 ; extra == 'docs'
Requires-Dist: sphinx-rtd-theme ==3.0.1 ; extra == 'docs'
Requires-Dist: autodoc-pydantic ==2.2.0 ; extra == 'docs'
Provides-Extra: torch
Requires-Dist: torch >=1.7 ; extra == 'torch'
Requires-Dist: wandb ; extra == 'torch'
